mcuuid/__init__.py
mcuuid/api.py
mcuuid/mcuuid.py
mcuuid/tools.py
mcuuid-1.1.0.dist-info/LICENSE
mcuuid-1.1.0.dist-info/METADATA
mcuuid-1.1.0.dist-info/WHEEL
mcuuid-1.1.0.dist-info/top_level.txt
mcuuid-1.1.0.dist-info/RECORD
