Metadata-Version: 2.1
Name: mcuuid
Version: 1.1.0
Summary: Getting Minecraft Player Information from Mojang API.
Home-page: https://github.com/clerie/mcuuid
Author: clerie
Author-email: hallo@clerie.de
Classifier: Programming Language :: Python :: 3
Classifier: License :: OSI Approved :: MIT License
Classifier: Operating System :: OS Independent
License-File: LICENSE
